GemBench/__init__.py
GemBench/benchmarking/GemBench.py
GemBench/benchmarking/__init__.py
GemBench/benchmarking/dataset/GemDatasets.py
GemBench/benchmarking/dataset/__init__.py
GemBench/benchmarking/dataset/CA_Prod/__init__.py
GemBench/benchmarking/dataset/CA_Prod/requirements.txt
GemBench/benchmarking/dataset/CA_Prod/src/CA_Prod_Dataset.py
GemBench/benchmarking/dataset/CA_Prod/src/__init__.py
GemBench/benchmarking/dataset/CA_Prod/src/dataset/__init__.py
GemBench/benchmarking/dataset/CA_Prod/src/dataset/cluster_labels.tsv
GemBench/benchmarking/dataset/CA_Prod/src/dataset/final_balanced_dataset.tsv
GemBench/benchmarking/dataset/CA_Prod/src/dataset/products.tsv
GemBench/benchmarking/dataset/CA_Prod/src/dataset/queries.tsv
GemBench/benchmarking/dataset/CA_Prod/src/utils/__init__.py
GemBench/benchmarking/dataset/CA_Prod/src/utils/convert_to_json.py
GemBench/benchmarking/dataset/CA_Prod/src/utils/logger.py
GemBench/benchmarking/dataset/CA_Prod/src/utils/parallel.py
GemBench/benchmarking/dataset/LM_Market/__init__.py
GemBench/benchmarking/dataset/LM_Market/categories.json
GemBench/benchmarking/dataset/LM_Market/prompts.json
GemBench/benchmarking/dataset/MT_Human/__init__.py
GemBench/benchmarking/dataset/MT_Human/categories.json
GemBench/benchmarking/dataset/MT_Human/prompts.json
GemBench/benchmarking/dataset/product/__init__.py
GemBench/benchmarking/dataset/product/products.json
GemBench/benchmarking/dataset/product/topics.json
GemBench/benchmarking/evaluator/__init__.py
GemBench/benchmarking/evaluator/base_evaluator.py
GemBench/benchmarking/evaluator/laaj_evaluator/__init__.py
GemBench/benchmarking/evaluator/laaj_evaluator/laaj_qualitative_evaluator.py
GemBench/benchmarking/evaluator/laaj_evaluator/scoring_principles.md
GemBench/benchmarking/evaluator/laaj_evaluator/agents/__init__.py
GemBench/benchmarking/evaluator/laaj_evaluator/agents/accuracy_agent.py
GemBench/benchmarking/evaluator/laaj_evaluator/agents/base_agent.py
gembench-1.0.9.dist-info/licenses/LICENSE
gembench-1.0.9.dist-info/METADATA
gembench-1.0.9.dist-info/WHEEL
gembench-1.0.9.dist-info/top_level.txt
gembench-1.0.9.dist-info/RECORD
