Metadata-Version: 2.4
Name: gembench
Version: 1.0.9
Summary: First comprehensive benchmark for Generative Engine Marketing (GEM), an emerging field that focuses on monetizing generative AI by seamlessly integrating advertisements into Large Language Model (LLM) responses. Our work addresses the core problem of ad-injected response (AIR) generation and provides a framework for its evaluation.
Home-page: https://github.com/Generative-Engine-Marketing/GEM-Bench
Author: GemBench Team(Silan Hu, Shiqi Zhang, Yimin Shi, Xiaokui Xiao)
Project-URL: Bug Reports, https://github.com/Generative-Engine-Marketing/GEM-Bench/issues
Project-URL: Source, https://github.com/Generative-Engine-Marketing/GEM-Bench
Project-URL: Documentation, https://github.com/Generative-Engine-Marketing/GEM-Bench/blob/main/README.md
Keywords: llm generative-engine-marketing gem benchmark machine-learning
Classifier: Development Status :: 3 - Alpha
Classifier: Intended Audience :: Developers
Classifier: Intended Audience :: Science/Research
Classifier: License :: OSI Approved :: Apache Software License
Classifier: Operating System :: OS Independent
Classifier: Programming Language :: Python :: 3
Classifier: Programming Language :: Python :: 3.8
Classifier: Programming Language :: Python :: 3.9
Classifier: Programming Language :: Python :: 3.10
Classifier: Programming Language :: Python :: 3.11
Classifier: Programming Language :: Python :: 3.12
Classifier: Topic :: Scientific/Engineering :: Artificial Intelligence
Classifier: Topic :: Software Development :: Libraries :: Python Modules
Requires-Python: >=3.8
Requires-Dist: openai
Requires-Dist: python-dotenv
Requires-Dist: nltk
Requires-Dist: numpy
Requires-Dist: sentence-transformers
Requires-Dist: scikit-learn>=1.0.0
Requires-Dist: pandas>=2.1.0
Requires-Dist: rich==14.0.0
Requires-Dist: openpyxl==3.1.5
Requires-Dist: pyfiglet==1.0.2
Requires-Dist: tenacity
Requires-Dist: aiolimiter
Requires-Dist: diskcache
Requires-Dist: cachetools
Requires-Dist: matplotlib
Requires-Dist: tiktoken
Dynamic: author
Dynamic: classifier
Dynamic: description
Dynamic: description-content-type
Dynamic: home-page
Dynamic: keywords
Dynamic: project-url
Dynamic: requires-python
Dynamic: summary
